Assignment2/3/ripple_adder.v
`timescale 1ns / 1ps

module nand2(input a, b, output y);
    assign #1 y = ~(a & b);
endmodule

module not_nand(input a, output y);
    nand2 n1(a, a, y);
endmodule

module and_nand(input a, b, output y);
    wire t;
    nand2 n1(a, b, t);
    nand2 n2(t, t, y);
endmodule

module or_nand(input a, b, output y);
    wire na, nb;
    not_nand n1(a, na);
    not_nand n2(b, nb);
    nand2 n3(na, nb, y);
endmodule

module xor_nand(input a, b, output y);
    wire t1, t2, t3;
    nand2 n1(a, b, t1);
    nand2 n2(a, t1, t2);
    nand2 n3(b, t1, t3);
    nand2 n4(t2, t3, y);
endmodule

module full_adder_nand(input a, b, cin, output sum, cout);
    wire axb, ab, bc, ac, t;

    xor_nand x1(a, b, axb);
    xor_nand x2(axb, cin, sum);

    and_nand a1(a, b, ab);
    and_nand a2(b, cin, bc);
    and_nand a3(a, cin, ac);

    or_nand o1(ab, bc, t);
    or_nand o2(t, ac, cout);
endmodule

module ripple_carry_adder_4bit(
    input  [3:0] A, B,
    input        Cin,
    output [3:0] Sum,
    output       Cout
);
    wire c1, c2, c3;

    full_adder_nand fa0(A[0], B[0], Cin,  Sum[0], c1);
    full_adder_nand fa1(A[1], B[1], c1,   Sum[1], c2);
    full_adder_nand fa2(A[2], B[2], c2,   Sum[2], c3);
    full_adder_nand fa3(A[3], B[3], c3,   Sum[3], Cout);
endmodule

Assignment2/3/tb_ripple_adder.v
`timescale 1ns / 1ps

module tb_ripple_adder;

    reg  [3:0] A, B;
    reg        Cin;
    wire [3:0] Sum;
    wire       Cout;

    ripple_carry_adder_4bit uut (
        .A(A), .B(B), .Cin(Cin),
        .Sum(Sum), .Cout(Cout)
    );

    initial begin
        $dumpfile("ripple_adder.vcd");
        $dumpvars(0, tb_ripple_adder);

        // Test 1: 15 + 15 + 1 = 31 (Overflow)
        A = 4'b1111; B = 4'b1111; Cin = 1; #100;

        // Test 2: 1 + 2 = 3
        A = 4'b0001; B = 4'b0010; Cin = 0; #100;

        // Test 3: Alternating bits with Cin
        A = 4'b1010; B = 4'b0101; Cin = 1; #100;

        // Test 4: All zeros
        A = 4'b0000; B = 4'b0000; Cin = 0; #100;

        // Test 5: Random mix
        A = 4'b1001; B = 4'b0110; Cin = 1; #100;

        $finish;
    end
endmodule

Assignment2/3/ripple_adder.vcd
$date
	Tue Apr 22 23:59:53 2025
$end
$version
	Icarus Verilog
$end
$timescale
	1ps
$end
$scope module tb_ripple_adder $end
$var wire 4 ! Sum [3:0] $end
$var wire 1 " Cout $end
$var reg 4 # A [3:0] $end
$var reg 4 $ B [3:0] $end
$var reg 1 % Cin $end
$scope module uut $end
$var wire 4 & A [3:0] $end
$var wire 4 ' B [3:0] $end
$var wire 1 % Cin $end
$var wire 1 ( c3 $end
$var wire 1 ) c2 $end
$var wire 1 * c1 $end
$var wire 4 + Sum [3:0] $end
$var wire 1 " Cout $end
$scope module fa0 $end
$var wire 1 , a $end
$var wire 1 - b $end
$var wire 1 % cin $end
$var wire 1 . t $end
$var wire 1 / sum $end
$var wire 1 * cout $end
$var wire 1 0 bc $end
$var wire 1 1 axb $end
$var wire 1 2 ac $end
$var wire 1 3 ab $end
$scope module a1 $end
$var wire 1 , a $end
$var wire 1 - b $end
$var wire 1 3 y $end
$var wire 1 4 t $end
$scope module n1 $end
$var wire 1 , a $end
$var wire 1 - b $end
$var wire 1 4 y $end
$upscope $end
$scope module n2 $end
$var wire 1 4 a $end
$var wire 1 4 b $end
$var wire 1 3 y $end
$upscope $end
$upscope $end
$scope module a2 $end
$var wire 1 - a $end
$var wire 1 % b $end
$var wire 1 0 y $end
$var wire 1 5 t $end
$scope module n1 $end
$var wire 1 - a $end
$var wire 1 % b $end
$var wire 1 5 y $end
$upscope $end
$scope module n2 $end
$var wire 1 5 a $end
$var wire 1 5 b $end
$var wire 1 0 y $end
$upscope $end
$upscope $end
$scope module a3 $end
$var wire 1 , a $end
$var wire 1 % b $end
$var wire 1 2 y $end
$var wire 1 6 t $end
$scope module n1 $end
$var wire 1 , a $end
$var wire 1 % b $end
$var wire 1 6 y $end
$upscope $end
$scope module n2 $end
$var wire 1 6 a $end
$var wire 1 6 b $end
$var wire 1 2 y $end
$upscope $end
$upscope $end
$scope module o1 $end
$var wire 1 3 a $end
$var wire 1 0 b $end
$var wire 1 . y $end
$var wire 1 7 nb $end
$var wire 1 8 na $end
$scope module n1 $end
$var wire 1 3 a $end
$var wire 1 8 y $end
$scope module n1 $end
$var wire 1 3 a $end
$var wire 1 3 b $end
$var wire 1 8 y $end
$upscope $end
$upscope $end
$scope module n2 $end
$var wire 1 0 a $end
$var wire 1 7 y $end
$scope module n1 $end
$var wire 1 0 a $end
$var wire 1 0 b $end
$var wire 1 7 y $end
$upscope $end
$upscope $end
$scope module n3 $end
$var wire 1 8 a $end
$var wire 1 7 b $end
$var wire 1 . y $end
$upscope $end
$upscope $end
$scope module o2 $end
$var wire 1 . a $end
$var wire 1 2 b $end
$var wire 1 * y $end
$var wire 1 9 nb $end
$var wire 1 : na $end
$scope module n1 $end
$var wire 1 . a $end
$var wire 1 : y $end
$scope module n1 $end
$var wire 1 . a $end
$var wire 1 . b $end
$var wire 1 : y $end
$upscope $end
$upscope $end
$scope module n2 $end
$var wire 1 2 a $end
$var wire 1 9 y $end
$scope module n1 $end
$var wire 1 2 a $end
$var wire 1 2 b $end
$var wire 1 9 y $end
$upscope $end
$upscope $end
$scope module n3 $end
$var wire 1 : a $end
$var wire 1 9 b $end
$var wire 1 * y $end
$upscope $end
$upscope $end
$scope module x1 $end
$var wire 1 , a $end
$var wire 1 - b $end
$var wire 1 1 y $end
$var wire 1 ; t3 $end
$var wire 1 < t2 $end
$var wire 1 = t1 $end
$scope module n1 $end
$var wire 1 , a $end
$var wire 1 - b $end
$var wire 1 = y $end
$upscope $end
$scope module n2 $end
$var wire 1 , a $end
$var wire 1 = b $end
$var wire 1 < y $end
$upscope $end
$scope module n3 $end
$var wire 1 - a $end
$var wire 1 = b $end
$var wire 1 ; y $end
$upscope $end
$scope module n4 $end
$var wire 1 < a $end
$var wire 1 ; b $end
$var wire 1 1 y $end
$upscope $end
$upscope $end
$scope module x2 $end
$var wire 1 1 a $end
$var wire 1 % b $end
$var wire 1 / y $end
$var wire 1 > t3 $end
$var wire 1 ? t2 $end
$var wire 1 @ t1 $end
$scope module n1 $end
$var wire 1 1 a $end
$var wire 1 % b $end
$var wire 1 @ y $end
$upscope $end
$scope module n2 $end
$var wire 1 1 a $end
$var wire 1 @ b $end
$var wire 1 ? y $end
$upscope $end
$scope module n3 $end
$var wire 1 % a $end
$var wire 1 @ b $end
$var wire 1 > y $end
$upscope $end
$scope module n4 $end
$var wire 1 ? a $end
$var wire 1 > b $end
$var wire 1 / y $end
$upscope $end
$upscope $end
$upscope $end
$scope module fa1 $end
$var wire 1 A a $end
$var wire 1 B b $end
$var wire 1 * cin $end
$var wire 1 C t $end
$var wire 1 D sum $end
$var wire 1 ) cout $end
$var wire 1 E bc $end
$var wire 1 F axb $end
$var wire 1 G ac $end
$var wire 1 H ab $end
$scope module a1 $end
$var wire 1 A a $end
$var wire 1 B b $end
$var wire 1 H y $end
$var wire 1 I t $end
$scope module n1 $end
$var wire 1 A a $end
$var wire 1 B b $end
$var wire 1 I y $end
$upscope $end
$scope module n2 $end
$var wire 1 I a $end
$var wire 1 I b $end
$var wire 1 H y $end
$upscope $end
$upscope $end
$scope module a2 $end
$var wire 1 B a $end
$var wire 1 * b $end
$var wire 1 E y $end
$var wire 1 J t $end
$scope module n1 $end
$var wire 1 B a $end
$var wire 1 * b $end
$var wire 1 J y $end
$upscope $end
$scope module n2 $end
$var wire 1 J a $end
$var wire 1 J b $end
$var wire 1 E y $end
$upscope $end
$upscope $end
$scope module a3 $end
$var wire 1 A a $end
$var wire 1 * b $end
$var wire 1 G y $end
$var wire 1 K t $end
$scope module n1 $end
$var wire 1 A a $end
$var wire 1 * b $end
$var wire 1 K y $end
$upscope $end
$scope module n2 $end
$var wire 1 K a $end
$var wire 1 K b $end
$var wire 1 G y $end
$upscope $end
$upscope $end
$scope module o1 $end
$var wire 1 H a $end
$var wire 1 E b $end
$var wire 1 C y $end
$var wire 1 L nb $end
$var wire 1 M na $end
$scope module n1 $end
$var wire 1 H a $end
$var wire 1 M y $end
$scope module n1 $end
$var wire 1 H a $end
$var wire 1 H b $end
$var wire 1 M y $end
$upscope $end
$upscope $end
$scope module n2 $end
$var wire 1 E a $end
$var wire 1 L y $end
$scope module n1 $end
$var wire 1 E a $end
$var wire 1 E b $end
$var wire 1 L y $end
$upscope $end
$upscope $end
$scope module n3 $end
$var wire 1 M a $end
$var wire 1 L b $end
$var wire 1 C y $end
$upscope $end
$upscope $end
$scope module o2 $end
$var wire 1 C a $end
$var wire 1 G b $end
$var wire 1 ) y $end
$var wire 1 N nb $end
$var wire 1 O na $end
$scope module n1 $end
$var wire 1 C a $end
$var wire 1 O y $end
$scope module n1 $end
$var wire 1 C a $end
$var wire 1 C b $end
$var wire 1 O y $end
$upscope $end
$upscope $end
$scope module n2 $end
$var wire 1 G a $end
$var wire 1 N y $end
$scope module n1 $end
$var wire 1 G a $end
$var wire 1 G b $end
$var wire 1 N y $end
$upscope $end
$upscope $end
$scope module n3 $end
$var wire 1 O a $end
$var wire 1 N b $end
$var wire 1 ) y $end
$upscope $end
$upscope $end
$scope module x1 $end
$var wire 1 A a $end
$var wire 1 B b $end
$var wire 1 F y $end
$var wire 1 P t3 $end
$var wire 1 Q t2 $end
$var wire 1 R t1 $end
$scope module n1 $end
$var wire 1 A a $end
$var wire 1 B b $end
$var wire 1 R y $end
$upscope $end
$scope module n2 $end
$var wire 1 A a $end
$var wire 1 R b $end
$var wire 1 Q y $end
$upscope $end
$scope module n3 $end
$var wire 1 B a $end
$var wire 1 R b $end
$var wire 1 P y $end
$upscope $end
$scope module n4 $end
$var wire 1 Q a $end
$var wire 1 P b $end
$var wire 1 F y $end
$upscope $end
$upscope $end
$scope module x2 $end
$var wire 1 F a $end
$var wire 1 * b $end
$var wire 1 D y $end
$var wire 1 S t3 $end
$var wire 1 T t2 $end
$var wire 1 U t1 $end
$scope module n1 $end
$var wire 1 F a $end
$var wire 1 * b $end
$var wire 1 U y $end
$upscope $end
$scope module n2 $end
$var wire 1 F a $end
$var wire 1 U b $end
$var wire 1 T y $end
$upscope $end
$scope module n3 $end
$var wire 1 * a $end
$var wire 1 U b $end
$var wire 1 S y $end
$upscope $end
$scope module n4 $end
$var wire 1 T a $end
$var wire 1 S b $end
$var wire 1 D y $end
$upscope $end
$upscope $end
$upscope $end
$scope module fa2 $end
$var wire 1 V a $end
$var wire 1 W b $end
$var wire 1 ) cin $end
$var wire 1 X t $end
$var wire 1 Y sum $end
$var wire 1 ( cout $end
$var wire 1 Z bc $end
$var wire 1 [ axb $end
$var wire 1 \ ac $end
$var wire 1 ] ab $end
$scope module a1 $end
$var wire 1 V a $end
$var wire 1 W b $end
$var wire 1 ] y $end
$var wire 1 ^ t $end
$scope module n1 $end
$var wire 1 V a $end
$var wire 1 W b $end
$var wire 1 ^ y $end
$upscope $end
$scope module n2 $end
$var wire 1 ^ a $end
$var wire 1 ^ b $end
$var wire 1 ] y $end
$upscope $end
$upscope $end
$scope module a2 $end
$var wire 1 W a $end
$var wire 1 ) b $end
$var wire 1 Z y $end
$var wire 1 _ t $end
$scope module n1 $end
$var wire 1 W a $end
$var wire 1 ) b $end
$var wire 1 _ y $end
$upscope $end
$scope module n2 $end
$var wire 1 _ a $end
$var wire 1 _ b $end
$var wire 1 Z y $end
$upscope $end
$upscope $end
$scope module a3 $end
$var wire 1 V a $end
$var wire 1 ) b $end
$var wire 1 \ y $end
$var wire 1 ` t $end
$scope module n1 $end
$var wire 1 V a $end
$var wire 1 ) b $end
$var wire 1 ` y $end
$upscope $end
$scope module n2 $end
$var wire 1 ` a $end
$var wire 1 ` b $end
$var wire 1 \ y $end
$upscope $end
$upscope $end
$scope module o1 $end
$var wire 1 ] a $end
$var wire 1 Z b $end
$var wire 1 X y $end
$var wire 1 a nb $end
$var wire 1 b na $end
$scope module n1 $end
$var wire 1 ] a $end
$var wire 1 b y $end
$scope module n1 $end
$var wire 1 ] a $end
$var wire 1 ] b $end
$var wire 1 b y $end
$upscope $end
$upscope $end
$scope module n2 $end
$var wire 1 Z a $end
$var wire 1 a y $end
$scope module n1 $end
$var wire 1 Z a $end
$var wire 1 Z b $end
$var wire 1 a y $end
$upscope $end
$upscope $end
$scope module n3 $end
$var wire 1 b a $end
$var wire 1 a b $end
$var wire 1 X y $end
$upscope $end
$upscope $end
$scope module o2 $end
$var wire 1 X a $end
$var wire 1 \ b $end
$var wire 1 ( y $end
$var wire 1 c nb $end
$var wire 1 d na $end
$scope module n1 $end
$var wire 1 X a $end
$var wire 1 d y $end
$scope module n1 $end
$var wire 1 X a $end
$var wire 1 X b $end
$var wire 1 d y $end
$upscope $end
$upscope $end
$scope module n2 $end
$var wire 1 \ a $end
$var wire 1 c y $end
$scope module n1 $end
$var wire 1 \ a $end
$var wire 1 \ b $end
$var wire 1 c y $end
$upscope $end
$upscope $end
$scope module n3 $end
$var wire 1 d a $end
$var wire 1 c b $end
$var wire 1 ( y $end
$upscope $end
$upscope $end
$scope module x1 $end
$var wire 1 V a $end
$var wire 1 W b $end
$var wire 1 [ y $end
$var wire 1 e t3 $end
$var wire 1 f t2 $end
$var wire 1 g t1 $end
$scope module n1 $end
$var wire 1 V a $end
$var wire 1 W b $end
$var wire 1 g y $end
$upscope $end
$scope module n2 $end
$var wire 1 V a $end
$var wire 1 g b $end
$var wire 1 f y $end
$upscope $end
$scope module n3 $end
$var wire 1 W a $end
$var wire 1 g b $end
$var wire 1 e y $end
$upscope $end
$scope module n4 $end
$var wire 1 f a $end
$var wire 1 e b $end
$var wire 1 [ y $end
$upscope $end
$upscope $end
$scope module x2 $end
$var wire 1 [ a $end
$var wire 1 ) b $end
$var wire 1 Y y $end
$var wire 1 h t3 $end
$var wire 1 i t2 $end
$var wire 1 j t1 $end
$scope module n1 $end
$var wire 1 [ a $end
$var wire 1 ) b $end
$var wire 1 j y $end
$upscope $end
$scope module n2 $end
$var wire 1 [ a $end
$var wire 1 j b $end
$var wire 1 i y $end
$upscope $end
$scope module n3 $end
$var wire 1 ) a $end
$var wire 1 j b $end
$var wire 1 h y $end
$upscope $end
$scope module n4 $end
$var wire 1 i a $end
$var wire 1 h b $end
$var wire 1 Y y $end
$upscope $end
$upscope $end
$upscope $end
$scope module fa3 $end
$var wire 1 k a $end
$var wire 1 l b $end
$var wire 1 ( cin $end
$var wire 1 m t $end
$var wire 1 n sum $end
$var wire 1 " cout $end
$var wire 1 o bc $end
$var wire 1 p axb $end
$var wire 1 q ac $end
$var wire 1 r ab $end
$scope module a1 $end
$var wire 1 k a $end
$var wire 1 l b $end
$var wire 1 r y $end
$var wire 1 s t $end
$scope module n1 $end
$var wire 1 k a $end
$var wire 1 l b $end
$var wire 1 s y $end
$upscope $end
$scope module n2 $end
$var wire 1 s a $end
$var wire 1 s b $end
$var wire 1 r y $end
$upscope $end
$upscope $end
$scope module a2 $end
$var wire 1 l a $end
$var wire 1 ( b $end
$var wire 1 o y $end
$var wire 1 t t $end
$scope module n1 $end
$var wire 1 l a $end
$var wire 1 ( b $end
$var wire 1 t y $end
$upscope $end
$scope module n2 $end
$var wire 1 t a $end
$var wire 1 t b $end
$var wire 1 o y $end
$upscope $end
$upscope $end
$scope module a3 $end
$var wire 1 k a $end
$var wire 1 ( b $end
$var wire 1 q y $end
$var wire 1 u t $end
$scope module n1 $end
$var wire 1 k a $end
$var wire 1 ( b $end
$var wire 1 u y $end
$upscope $end
$scope module n2 $end
$var wire 1 u a $end
$var wire 1 u b $end
$var wire 1 q y $end
$upscope $end
$upscope $end
$scope module o1 $end
$var wire 1 r a $end
$var wire 1 o b $end
$var wire 1 m y $end
$var wire 1 v nb $end
$var wire 1 w na $end
$scope module n1 $end
$var wire 1 r a $end
$var wire 1 w y $end
$scope module n1 $end
$var wire 1 r a $end
$var wire 1 r b $end
$var wire 1 w y $end
$upscope $end
$upscope $end
$scope module n2 $end
$var wire 1 o a $end
$var wire 1 v y $end
$scope module n1 $end
$var wire 1 o a $end
$var wire 1 o b $end
$var wire 1 v y $end
$upscope $end
$upscope $end
$scope module n3 $end
$var wire 1 w a $end
$var wire 1 v b $end
$var wire 1 m y $end
$upscope $end
$upscope $end
$scope module o2 $end
$var wire 1 m a $end
$var wire 1 q b $end
$var wire 1 " y $end
$var wire 1 x nb $end
$var wire 1 y na $end
$scope module n1 $end
$var wire 1 m a $end
$var wire 1 y y $end
$scope module n1 $end
$var wire 1 m a $end
$var wire 1 m b $end
$var wire 1 y y $end
$upscope $end
$upscope $end
$scope module n2 $end
$var wire 1 q a $end
$var wire 1 x y $end
$scope module n1 $end
$var wire 1 q a $end
$var wire 1 q b $end
$var wire 1 x y $end
$upscope $end
$upscope $end
$scope module n3 $end
$var wire 1 y a $end
$var wire 1 x b $end
$var wire 1 " y $end
$upscope $end
$upscope $end
$scope module x1 $end
$var wire 1 k a $end
$var wire 1 l b $end
$var wire 1 p y $end
$var wire 1 z t3 $end
$var wire 1 { t2 $end
$var wire 1 | t1 $end
$scope module n1 $end
$var wire 1 k a $end
$var wire 1 l b $end
$var wire 1 | y $end
$upscope $end
$scope module n2 $end
$var wire 1 k a $end
$var wire 1 | b $end
$var wire 1 { y $end
$upscope $end
$scope module n3 $end
$var wire 1 l a $end
$var wire 1 | b $end
$var wire 1 z y $end
$upscope $end
$scope module n4 $end
$var wire 1 { a $end
$var wire 1 z b $end
$var wire 1 p y $end
$upscope $end
$upscope $end
$scope module x2 $end
$var wire 1 p a $end
$var wire 1 ( b $end
$var wire 1 n y $end
$var wire 1 } t3 $end
$var wire 1 ~ t2 $end
$var wire 1 !" t1 $end
$scope module n1 $end
$var wire 1 p a $end
$var wire 1 ( b $end
$var wire 1 !" y $end
$upscope $end
$scope module n2 $end
$var wire 1 p a $end
$var wire 1 !" b $end
$var wire 1 ~ y $end
$upscope $end
$scope module n3 $end
$var wire 1 ( a $end
$var wire 1 !" b $end
$var wire 1 } y $end
$upscope $end
$scope module n4 $end
$var wire 1 ~ a $end
$var wire 1 } b $end
$var wire 1 n y $end
$upscope $end
$upscope $end
$upscope $end
$upscope $end
$upscope $end
$enddefinitions $end
$comment Show the parameter values. $end
$dumpall
$end
#0
$dumpvars
x!"
x~
x}
x|
x{
xz
xy
xx
xw
xv
xu
xt
xs
xr
xq
xp
xo
xn
xm
1l
1k
xj
xi
xh
xg
xf
xe
xd
xc
xb
xa
x`
x_
x^
x]
x\
x[
xZ
xY
xX
1W
1V
xU
xT
xS
xR
xQ
xP
xO
xN
xM
xL
xK
xJ
xI
xH
xG
xF
xE
xD
xC
1B
1A
x@
x?
x>
x=
x<
x;
x:
x9
x8
x7
x6
x5
x4
x3
x2
x1
x0
x/
x.
1-
1,
bx +
x*
x)
x(
b1111 '
b1111 &
1%
b1111 $
b1111 #
x"
bx !
$end
#1000
05
04
06
0=
0I
0R
0^
0g
0s
0|
#2000
10
13
12
1<
1;
1H
1Q
1P
1]
1f
1e
1r
1{
1z
#3000
07
08
09
01
0M
0F
0b
0[
0w
0p
#4000
1.
1*
1@
1?
1C
1U
1T
1X
1j
1i
1m
1!"
1~
#5000
0:
0J
0K
0>
0O
0S
0d
0y
#6000
1E
1G
1/
1)
bx11 !
bx11 +
1D
1(
1"
#7000
0L
0N
0_
0`
0h
0t
0u
0}
#8000
1Z
1\
1Y
1o
1q
b1111 !
b1111 +
1n
#9000
0a
0c
0v
0x
#100000
0-
0W
0l
0A
0V
0k
0%
b10 $
b10 '
b1 #
b1 &
#101000
14
1=
1_
1t
1I
1K
1R
1^
1`
1g
1s
1u
1|
15
16
1>
#102000
03
0<
0Z
0o
0H
0G
0P
0]
0\
0r
0q
00
02
b1110 !
b1110 +
0/
#103000
18
11
1a
1v
1M
1N
1F
1b
1c
1w
1x
17
19
#104000
0?
0U
0T
0X
0m
0.
#105000
b1111 !
b1111 +
1/
1T
1S
1d
1y
1:
#106000
b1101 !
b1101 +
0D
0(
0"
0*
#107000
1}
1J
1U
#108000
b101 !
b101 +
0n
0E
0T
#109000
1L
b111 !
b111 +
1D
#110000
0C
#111000
1O
#112000
0)
#113000
1h
#114000
b11 !
b11 +
0Y
#200000
1-
0B
1W
0,
1A
1k
1%
b101 $
b101 '
b1010 #
b1010 &
#201000
0;
1P
0e
1<
0Q
0{
05
0@
0>
#202000
1[
1p
10
1?
1>
#203000
0i
0~
07
b10 !
b10 +
0/
#204000
1Y
b1110 !
b1110 +
1n
1.
#205000
0:
#206000
1*
#207000
0K
0U
0S
#208000
1G
1T
1S
#209000
0N
b1100 !
b1100 +
0D
#210000
1)
#211000
0_
0j
0h
#212000
1Z
1i
1h
#213000
0a
b1000 !
b1000 +
0Y
#214000
1X
#215000
0d
#216000
1(
#217000
0u
0!"
0}
#218000
1q
1~
1}
#219000
0x
b0 !
b0 +
0n
#220000
1"
#300000
0-
0W
0A
0k
0%
b0 $
b0 '
b0 #
b0 &
#301000
1;
1_
1e
1K
1Q
1u
1{
15
1@
#302000
01
0Z
0[
0G
0F
0q
0p
00
0?
#303000
1?
1a
1j
1N
1U
1x
1!"
17
b1 !
b1 +
1/
#304000
b0 !
b0 +
0/
0X
0h
0)
0S
0"
0}
0.
#305000
1d
1Y
1h
1D
b1110 !
b1110 +
1n
1:
#306000
0(
b1010 !
b1010 +
0Y
0*
#307000
1}
1S
#308000
0n
b0 !
b0 +
0D
#400000
1B
1W
1,
1k
1%
b110 $
b110 '
b1001 #
b1001 &
#401000
0P
0e
0<
0{
06
0>
#402000
1F
1[
11
1p
12
b1 !
b1 +
1/
#403000
0T
0i
0@
0?
0~
09
#404000
1D
1Y
1?
1>
b1111 !
b1111 +
1n
1*
#405000
b1110 !
b1110 +
0/
0J
0U
0S
#406000
1E
1T
1S
#407000
0L
b1100 !
b1100 +
0D
#408000
1C
#409000
0O
#410000
1)
#411000
0_
0j
0h
#412000
1Z
1i
1h
#413000
0a
b1000 !
b1000 +
0Y
#414000
1X
#415000
0d
#416000
1(
#417000
0u
0!"
0}
#418000
1q
1~
1}
#419000
0x
b0 !
b0 +
0n
#420000
1"
